{
  "tags": [
    {
      "name": "release",
      "version": "1.21.1",
      "commit": "9125a75",
      "upstream": "Releases",
      "lastUpdated": "2021-03-26T01:52:01.053Z"
    },
    {
      "name": "testing",
      "version": "",
      "commit": "",
      "upstream": "",
      "lastUpdated": ""
    },
    {
      "name": "nightly",
      "version": "e16277c07d58ddbb749f4a60bc05924f4a5af146",
      "commit": "335cfcf",
      "upstream": "Every commit to develop",
      "lastUpdated": "2021-03-29T02:00:09.875Z"
    }
  ],
  "pulls": 511458,
  "stars": 4
}
